genpasswd/__init__.py
genpasswd/cli.py
genpasswd/generate.py
genpasswd_everdrone-2.0.3.dist-info/METADATA
genpasswd_everdrone-2.0.3.dist-info/WHEEL
genpasswd_everdrone-2.0.3.dist-info/entry_points.txt
genpasswd_everdrone-2.0.3.dist-info/top_level.txt
genpasswd_everdrone-2.0.3.dist-info/RECORD
