Metadata-Version: 2.1
Name: genpasswd-everdrone
Version: 2.0.3
Summary: Password Generator
Home-page: https://github.com/everdrone/genpasswd2
Author: Giorgio Tropiano
Author-email: giorgiotropiano@gmail.com
License: MIT
Classifier: Programming Language :: Python :: 3
Classifier: License :: OSI Approved :: MIT License
Classifier: Operating System :: OS Independent
Requires-Python: >=3.7.5
